pythongram/__init__.py
pythongram/config.py
pythongram/modules/__init__.py
pythongram/modules/connection.py
pythongram/modules/user.py
pythongram/pythongram.py
pythongram/utils.py
pythongram/version.py
pythongram-0.1.0.dist-info/LICENSE
pythongram-0.1.0.dist-info/WHEEL
pythongram-0.1.0.dist-info/METADATA
pythongram-0.1.0.dist-info/RECORD
